pirebok/__init__.py
pirebok/cli.py
pirebok/fuzzers/__init__.py
pirebok/fuzzers/fuzzer.py
pirebok/fuzzers/fuzzer_builder.py
pirebok/fuzzers/fuzzer_transformer_resolver_visitor.py
pirebok/fuzzers/fuzzer_visitor.py
pirebok/fuzzers/generic/__init__.py
pirebok/fuzzers/generic/random_generic_fuzzer.py
pirebok/fuzzers/generic_fuzzer.py
pirebok/fuzzers/sql/__init__.py
pirebok/fuzzers/sql/guided_random_sql_fuzzer.py
pirebok/fuzzers/sql/random_sql_fuzzer.py
pirebok/fuzzers/sql_fuzzer.py
pirebok/pirebok.py
pirebok/transformers/__init__.py
pirebok/transformers/generic/__init__.py
pirebok/transformers/generic/random_case_swapping_transformer.py
pirebok/transformers/generic/random_comment_removing_transformer.py
pirebok/transformers/generic/random_comment_rewriting_transformer.py
pirebok/transformers/generic/random_number_encoding_transformer.py
pirebok/transformers/generic/random_space_substitution_transformer.py
pirebok/transformers/generic_transformer.py
pirebok/transformers/sql/__init__.py
pirebok/transformers/sql/random_keyword_swapping_transformer.py
pirebok/transformers/sql/random_logical_invariant_appender_transformer.py
pirebok/transformers/sql/random_tautology_swapping_transofmer.py
pirebok/transformers/sql_transformer.py
pirebok/transformers/transformer.py
pirebok/transformers/utils.py
pirebok-0.2.0.dist-info/entry_points.txt
pirebok-0.2.0.dist-info/LICENSE
pirebok-0.2.0.dist-info/WHEEL
pirebok-0.2.0.dist-info/METADATA
pirebok-0.2.0.dist-info/RECORD
